MANIFEST.in
README
config_local.py
serve.py
setup.py
src/invenio_devserver/__init__.py
src/invenio_devserver/config.py
src/invenio_devserver/mailserve.py
src/invenio_devserver/serve.py
src/invenio_devserver/webserver.py
src/invenio_devserver/webserver_ssl.py
src/invenio_devserver/wsgi.py
src/invenio_devserver.egg-info/PKG-INFO
src/invenio_devserver.egg-info/SOURCES.txt
src/invenio_devserver.egg-info/dependency_links.txt
src/invenio_devserver.egg-info/entry_points.txt
src/invenio_devserver.egg-info/not-zip-safe
src/invenio_devserver.egg-info/requires.txt
src/invenio_devserver.egg-info/top_level.txt