Metadata-Version: 1.1
Name: invenio-devserver
Version: 0.5
Summary: An HTTP server for Invenio with automatic code reloading
Home-page: https://bitbucket.org/osso/invenio-devserver
Author: Alessio Deiana
Author-email: alessio.deiana@cern.ch
License: GPL
Keywords: invenio http server
Platform: UNKNOWN
Classifier: Development Status :: 3 - Alpha
Classifier: Intended Audience :: Developers
Classifier: Topic :: Utilities
Classifier: Topic :: Internet :: WWW/HTTP :: HTTP Servers
Classifier: Topic :: Internet :: WWW/HTTP :: WSGI :: Server
Classifier: License :: OSI Approved :: GNU General Public License (GPL)
